dauricum/__init__.py
dauricum/__main__.py
dauricum/cli/__init__.py
dauricum/tools/logger.py
dauricum/tools/utils.py
dauricum/transformers/base.py
dauricum/transformers/biopaque_transformer.py
dauricum/transformers/call_transformer.py
dauricum/transformers/controlflow_transformer.py
dauricum/transformers/exceptionjmp_transformer.py
dauricum/transformers/format_transformer.py
dauricum/transformers/function_transformer.py
dauricum/transformers/import_transformer.py
dauricum/transformers/junk_transformer.py
dauricum/transformers/number_transformer.py
dauricum/transformers/outline_transformer.py
dauricum/transformers/renamer_transformer.py
dauricum/transformers/string_transformer.py
dauricum-1.0.dist-info/METADATA
dauricum-1.0.dist-info/WHEEL
dauricum-1.0.dist-info/top_level.txt
dauricum-1.0.dist-info/RECORD
