Metadata-Version: 2.1
Name: dauricum
Version: 1.0
Summary: python 3.10+ obfuscator
Author-email: nighty1337 <mg938436@gmail.com>
Project-URL: Homepage, https://github.com/Maxdsdsdsd/dauricum
Project-URL: Bug Tracker, https://github.com/Maxdsdsdsd/dauricum/issues
Classifier: Programming Language :: Python :: 3
Classifier: License :: OSI Approved :: MIT License
Classifier: Operating System :: Microsoft :: Windows
Requires-Python: >=3.10
